README.md
setup.cfg
setup.py
autocontainer/__init__.py
autocontainer/autocontainer.py
autocontainer.egg-info/PKG-INFO
autocontainer.egg-info/SOURCES.txt
autocontainer.egg-info/dependency_links.txt
autocontainer.egg-info/top_level.txt