Metadata-Version: 2.1
Name: autocontainer
Version: 1.0.4
Summary: A modern typing based service container and dependency injector.
Home-page: https://github.com/Hedronium/autocontainer
Author: Omran Jamal
Author-email: o.jamal97@gmail.com
License: MIT
Download-URL: https://github.com/Hedronium/autocontainer/archive/v1.0.4.tar.gz
Keywords: container,dependency,injection,inversion,control,service
Platform: UNKNOWN
Classifier: Development Status :: 5 - Production/Stable
Classifier: Intended Audience :: Developers
Classifier: Topic :: Software Development :: Libraries
Classifier: Topic :: Software Development :: Libraries :: Python Modules
Classifier: Topic :: Software Development :: Object Brokering
Classifier: License :: OSI Approved :: MIT License
Requires-Python: >=3.5
